SublimeTextZhongwenWendangShiyongshouce/README.md
SublimeTextZhongwenWendangShiyongshouce/__init__.py
SublimeTextZhongwenWendangShiyongshouce/__main__.py
SublimeTextZhongwenWendangShiyongshouce/file.epub
SublimeTextZhongwenWendangShiyongshouce/index.html
SublimeTextZhongwenWendangShiyongshouce/css/__init__.py
SublimeTextZhongwenWendangShiyongshouce/css/annotations.css
SublimeTextZhongwenWendangShiyongshouce/css/main.css
SublimeTextZhongwenWendangShiyongshouce/css/normalize.css
SublimeTextZhongwenWendangShiyongshouce/css/popup.css
SublimeTextZhongwenWendangShiyongshouce/font/__init__.py
SublimeTextZhongwenWendangShiyongshouce/font/fontello.eot
SublimeTextZhongwenWendangShiyongshouce/font/fontello.svg
SublimeTextZhongwenWendangShiyongshouce/font/fontello.ttf
SublimeTextZhongwenWendangShiyongshouce/font/fontello.woff
SublimeTextZhongwenWendangShiyongshouce/img/__init__.py
SublimeTextZhongwenWendangShiyongshouce/img/annotator-glyph-sprite.png
SublimeTextZhongwenWendangShiyongshouce/img/annotator-icon-sprite.png
SublimeTextZhongwenWendangShiyongshouce/img/apple-touch-icon.png
SublimeTextZhongwenWendangShiyongshouce/img/cancelfullscreen.png
SublimeTextZhongwenWendangShiyongshouce/img/close.png
SublimeTextZhongwenWendangShiyongshouce/img/fullscreen.png
SublimeTextZhongwenWendangShiyongshouce/img/loader.gif
SublimeTextZhongwenWendangShiyongshouce/img/menu-icon.png
SublimeTextZhongwenWendangShiyongshouce/img/save.png
SublimeTextZhongwenWendangShiyongshouce/img/saved.png
SublimeTextZhongwenWendangShiyongshouce/img/settings-s.png
SublimeTextZhongwenWendangShiyongshouce/img/settings.png
SublimeTextZhongwenWendangShiyongshouce/img/star.png
SublimeTextZhongwenWendangShiyongshouce/js/__init__.py
SublimeTextZhongwenWendangShiyongshouce/js/epub.js
SublimeTextZhongwenWendangShiyongshouce/js/epub.min.js
SublimeTextZhongwenWendangShiyongshouce/js/epub.min.map
SublimeTextZhongwenWendangShiyongshouce/js/hooks.min.js
SublimeTextZhongwenWendangShiyongshouce/js/hooks.min.map
sublime_text_zhongwen_wendang_shiyongshouce-2024.3.2.0.dist-info/METADATA
sublime_text_zhongwen_wendang_shiyongshouce-2024.3.2.0.dist-info/WHEEL
sublime_text_zhongwen_wendang_shiyongshouce-2024.3.2.0.dist-info/entry_points.txt
sublime_text_zhongwen_wendang_shiyongshouce-2024.3.2.0.dist-info/top_level.txt
sublime_text_zhongwen_wendang_shiyongshouce-2024.3.2.0.dist-info/RECORD
